{
  "games": [
    {
      "title": "GTA V",
      "platform": "PS5"
    },
    {
      "title": "NBA",
      "platform": "PS5"
    },
    {
      "title": "God Of War",
      "platform": "PS5"
    },
    {
      "title": "Call Of Duty",
      "platform": "PS4"
    },
    {
      "title": "Fortnite",
      "platform": "PS4"
    },
    {
      "title": "Mario Kart",
      "platform": "NITENDOSWITCH"
    },
    {
      "title": "Mario 3D",
      "platform": "NITENDOSWITCH"
    },
    {
      "title": "Pokemon",
      "platform": "NITENDOSWITCH"
    },
    {
      "title": "Valorant",
      "platform": "PC"
    },
    {
      "title": "Roblox",
      "platform": "PC"
    }
  ]
}
